lib_headspace/__init__.py
lib_headspace/py.typed
lib_headspace/api/__init__.py
lib_headspace/api/client.py
lib_headspace/api/constants.py
lib_headspace/api/util/__init__.py
lib_headspace/api/util/convert.py
lib_headspace-0.1.0.dist-info/METADATA
lib_headspace-0.1.0.dist-info/WHEEL
lib_headspace-0.1.0.dist-info/RECORD
