Metadata-Version: 2.3
Name: lib-headspace
Version: 0.1.0
Summary: Basic API client for Headspace
Author: Karl Quinsland
Requires-Python: >=3.13
Requires-Dist: aiohttp>=3.11.7
Requires-Dist: aioresponses>=0.7.7
Requires-Dist: brotlipy>=0.7.0
Requires-Dist: pyjwt>=2.10.0
Requires-Dist: structlog>=24.4.0
